{
    "items": [{
        "title": "ENDER'S GAME",
        "author": "Orson Scott Card"
    }, {
        "title": "DUNE",
        "author": "Frank Herbert"
    }, {
        "title": "THE HITCHHIKER'S GUIDE TO THE GALAXY",
        "author": "Douglas Adams"
    }, {
        "title": "THE LORD OF THE RINGS",
        "author": "J. R. R. Tolkien"
    }, {
        "title": "NINETEEN EIGHTY-FOUR",
        "author": "George Orwell"
    }, {
        "title": "AMERICAN GODS",
        "author": "Neil Gaiman"
    }, {
        "title": "THE HOBBIT",
        "author": "J. R. R. Tolkien"
    }, {
        "title": "THE FOREVER WAR",
        "author": "Joe Haldeman"
    }, {
        "title": "NEUROMANCER",
        "author": "William Gibson"
    }, {
        "title": "FAHRENHEIT 451",
        "author": "Ray Bradbury"
    }, {
        "title": "RENDEZVOUS WITH RAMA",
        "author": "Arthur C. Clarke"
    }, {
        "title": "HARRY POTTER AND THE PRISONER OF AZKABAN",
        "author": "J. K. Rowling"
    }, {
        "title": "DO ANDROIDS DREAM OF ELECTRIC SHEEP?",
        "author": "Philip K. Dick"
    }, {
        "title": "HARRY POTTER AND THE GOBLET OF FIRE",
        "author": "J. K. Rowling"
    }, {
        "title": "STRANGER IN A STRANGE LAND",
        "author": "Robert A. Heinlein"
    }, {
        "title": "HYPERION",
        "author": "Dan Simmons"
    }, {
        "title": "A GAME OF THRONES",
        "author": "George R. R. Martin"
    }, {
        "title": "HARRY POTTER AND THE SORCERER'S STONE",
        "author": "J. K. Rowling"
    }, {
        "title": "RINGWORLD",
        "author": "Larry Niven"
    }, {
        "title": "SPEAKER FOR THE DEAD",
        "author": "Orson Scott Card"
    }, {
        "title": "ANIMAL FARM",
        "author": "George Orwell"
    }, {
        "title": "BRAVE NEW WORLD",
        "author": "Aldous Huxley"
    }, {
        "title": "STARSHIP TROOPERS",
        "author": "Robert A. Heinlein"
    }, {
        "title": "THE LEFT HAND OF DARKNESS",
        "author": "Ursula K. Le Guin"
    }, {
        "title": "THE FOUNDATION TRILOGY",
        "author": "Isaac Asimov"
    }, {
        "title": "SLAUGHTERHOUSE - FIVE",
        "author": "Kurt Vonnegut, Jr."
    }, {
        "title": "FLOWERS FOR ALGERNON",
        "author": "Daniel Keyes"
    }, {
        "title": "FOUNDATION",
        "author": "Isaac Asimov"
    }, {
        "title": "THE FELLOWSHIP OF THE RING",
        "author": "J. R. R. Tolkien"
    }, {
        "title": "A CANTICLE FOR LEIBOWITZ",
        "author": "Walter M. Miller, Jr."
    }, {
        "title": "THE TIME MACHINE",
        "author": "H. G. Wells"
    }, {
        "title": "THE TWO TOWERS",
        "author": "J. R. R. Tolkien"
    }, {
        "title": "FRANKENSTEIN",
        "author": "Mary Shelley"
    }, {
        "title": "CHILDHOOD'S END",
        "author": "Arthur C. Clarke"
    }, {
        "title": "THE MAN IN THE HIGH CASTLE",
        "author": "Philip K. Dick"
    }, {
        "title": "THE RETURN OF THE KING",
        "author": "J. R. R. Tolkien"
    }, {
        "title": "THE MOON IS A HARSH MISTRESS",
        "author": "Robert A. Heinlein"
    }, {
        "title": "A CLASH OF KINGS",
        "author": "George R. R. Martin"
    }, {
        "title": "I, ROBOT",
        "author": "Isaac Asimov"
    }, {
        "title": "HARRY POTTER AND THE CHAMBER OF SECRETS",
        "author": "J. K. Rowling"
    }, {
        "title": "A STORM OF SWORDS",
        "author": "George R. R. Martin"
    }, {
        "title": "THE MARTIAN CHRONICLES",
        "author": "Ray Bradbury"
    }, {
        "title": "THE FALL OF HYPERION",
        "author": "Dan Simmons"
    }, {
        "title": "2001",
        "author": "Arthur C. Clarke"
    }, {
        "title": "SNOW CRASH",
        "author": "Neal Stephenson"
    }, {
        "title": "OLD MAN'S WAR",
        "author": "John Scalzi"
    }, {
        "title": "HARRY POTTER AND THE HALF-BLOOD PRINCE",
        "author": "J. K. Rowling"
    }, {
        "title": "A FEAST FOR CROWS",
        "author": "George R. R. Martin"
    }, {
        "title": "THE WAR OF THE WORLDS",
        "author": "H. G. Wells"
    }, {
        "title": "HARRY POTTER AND THE ORDER OF THE PHOENIX",
        "author": "J. K. Rowling"
    }, {
        "title": "THE HANDMAID'S TALE",
        "author": "Margaret Atwood"
    }, {
        "title": "HARRY POTTER AND THE DEATHLY HALLOWS",
        "author": "J. K. Rowling"
    }, {
        "title": "THE RESTAURANT AT THE END OF THE UNIVERSE",
        "author": "Douglas Adams"
    }, {
        "title": "THE HUNGER GAMES",
        "author": "Suzanne Collins"
    }, {
        "title": "THE DISPOSSESSED",
        "author": "Ursula K. Le Guin"
    }, {
        "title": "GATEWAY",
        "author": "Frederik Pohl"
    }, {
        "title": "LORD OF THE FLIES",
        "author": "William Golding"
    }, {
        "title": "I AM LEGEND",
        "author": "Richard Matheson"
    }, {
        "title": "RED MARS",
        "author": "Kim Stanley Robinson"
    }, {
        "title": "THE STAND",
        "author": "Stephen King"
    }, {
        "title": "THE STARS MY DESTINATION",
        "author": "Alfred Bester"
    }, {
        "title": "THE DEMOLISHED MAN",
        "author": "Alfred Bester"
    }, {
        "title": "DOOMSDAY BOOK",
        "author": "Connie Willis"
    }, {
        "title": "JONATHAN STRANGE & MR. NORRELL",
        "author": "Susanna Clarke"
    }, {
        "title": "A DANCE WITH DRAGONS",
        "author": "George R. R. Martin"
    }, {
        "title": "FOUNDATION'S EDGE",
        "author": "Isaac Asimov"
    }, {
        "title": "LIFE, THE UNIVERSE AND EVERYTHING",
        "author": "Douglas Adams"
    }, {
        "title": "A WIZARD OF EARTHSEA",
        "author": "Ursula K. Le Guin"
    }, {
        "title": "XENOCIDE",
        "author": "Orson Scott Card"
    }, {
        "title": "CHILDREN OF DUNE",
        "author": "Frank Herbert"
    }, {
        "title": "ANCILLARY JUSTICE",
        "author": "Ann Leckie"
    }, {
        "title": "A FIRE UPON THE DEEP",
        "author": "Vernor Vinge"
    }, {
        "title": "THE COLOR OF MAGIC",
        "author": "Terry Pratchett"
    }, {
        "title": "THE WINDUP GIRL",
        "author": "Paolo Bacigalupi"
    }, {
        "title": "FOUNDATION AND EMPIRE",
        "author": "Isaac Asimov"
    }, {
        "title": "PERDIDO STREET STATION",
        "author": "China Miéville"
    }, {
        "title": "THE DIAMOND AGE",
        "author": "Neal Stephenson"
    }, {
        "title": "THE GRAVEYARD BOOK",
        "author": "Neil Gaiman"
    }, {
        "title": "CRYPTONOMICON",
        "author": "Neal Stephenson"
    }, {
        "title": "THE GOLDEN COMPASS",
        "author": "Philip Pullman"
    }, {
        "title": "SECOND FOUNDATION",
        "author": "Isaac Asimov"
    }, {
        "title": "THE CAVES OF STEEL",
        "author": "Isaac Asimov"
    }, {
        "title": "CAT'S CRADLE",
        "author": "Kurt Vonnegut, Jr."
    }, {
        "title": "THE CITY & THE CITY",
        "author": "China Miéville"
    }, {
        "title": "THE GUNSLINGER",
        "author": "Stephen King"
    }, {
        "title": "GOOD OMENS",
        "author": "Neil GaimanTerry Pratchett"
    }, {
        "title": "THE LION, THE WITCH AND THE WARDROBE",
        "author": "C. S. Lewis"
    }, {
        "title": "A CLOCKWORK ORANGE",
        "author": "Anthony Burgess"
    }, {
        "title": "REDSHIRTS",
        "author": "John Scalzi"
    }, {
        "title": "DRACULA",
        "author": "Bram Stoker"
    }, {
        "title": "WATCHMEN",
        "author": "Alan MooreDave Gibbons"
    }, {
        "title": "THE GODS THEMSELVES",
        "author": "Isaac Asimov"
    }, {
        "title": "THE MOTE IN GOD'S EYE",
        "author": "Larry NivenJerry Pournelle"
    }, {
        "title": "CATCHING FIRE",
        "author": "Suzanne Collins"
    }, {
        "title": "DUNE MESSIAH",
        "author": "Frank Herbert"
    }, {
        "title": "NEVERWHERE",
        "author": "Neil Gaiman"
    }, {
        "title": "THE SILMARILLION",
        "author": "J. R. R. Tolkien"
    }, {
        "title": "MOCKINGJAY",
        "author": "Suzanne Collins"
    }, {
        "title": "LORD OF LIGHT",
        "author": "Roger Zelazny"
    }, {
        "title": "ALICE'S ADVENTURES IN WONDERLAND",
        "author": "Lewis Carroll"
    }, {
        "title": "CONSIDER PHLEBAS",
        "author": "Iain M. Banks"
    }, {
        "title": "SO LONG, AND THANKS FOR ALL THE FISH",
        "author": "Douglas Adams"
    }, {
        "title": "STARTIDE RISING",
        "author": "David Brin"
    }, {
        "title": "SPIN",
        "author": "Robert Charles Wilson"
    }, {
        "title": "ANANSI BOYS",
        "author": "Neil Gaiman"
    }, {
        "title": "THE ROAD",
        "author": "Cormac McCarthy"
    }, {
        "title": "THE EYE OF THE WORLD",
        "author": "Robert Jordan"
    }, {
        "title": "UBIK",
        "author": "Philip K. Dick"
    }, {
        "title": "THE SHINING",
        "author": "Stephen King"
    }, {
        "title": "A SCANNER DARKLY",
        "author": "Philip K. Dick"
    }, {
        "title": "TO YOUR SCATTERED BODIES GO",
        "author": "Philip José Farmer"
    }, {
        "title": "THE AMBER SPYGLASS",
        "author": "Philip Pullman"
    }, {
        "title": "20,000 LEAGUES UNDER THE SEA",
        "author": "Jules Verne"
    }, {
        "title": "STARDUST",
        "author": "Neil Gaiman"
    }, {
        "title": "ANATHEM",
        "author": "Neal Stephenson"
    }, {
        "title": "THE SHADOW OF THE TORTURER",
        "author": "Gene Wolfe"
    }, {
        "title": "THE LATHE OF HEAVEN",
        "author": "Ursula K. Le Guin"
    }, {
        "title": "INTERVIEW WITH THE VAMPIRE",
        "author": "Anne Rice"
    }, {
        "title": "DRAGONFLIGHT",
        "author": "Anne McCaffrey"
    }, {
        "title": "2010",
        "author": "Arthur C. Clarke"
    }, {
        "title": "THE DAY OF THE TRIFFIDS",
        "author": "John Wyndham"
    }, {
        "title": "THE SIRENS OF TITAN",
        "author": "Kurt Vonnegut, Jr."
    }, {
        "title": "LEVIATHAN WAKES",
        "author": "James S. A. Corey"
    }, {
        "title": "A DEEPNESS IN THE SKY",
        "author": "Vernor Vinge"
    }, {
        "title": "THE NAME OF THE WIND",
        "author": "Patrick Rothfuss"
    }, {
        "title": "IT",
        "author": "Stephen King"
    }, {
        "title": "THE STRANGE CASE OF DR. JEKYLL AND MR. HYDE",
        "author": "Robert Louis Stevenson"
    }, {
        "title": "GREEN MARS",
        "author": "Kim Stanley Robinson"
    }, {
        "title": "THE CHRONICLES OF NARNIA",
        "author": "C. S. Lewis"
    }, {
        "title": "AMONG OTHERS",
        "author": "Jo Walton"
    }, {
        "title": "ENDER'S SHADOW",
        "author": "Orson Scott Card"
    }, {
        "title": "FOUNDATION AND EARTH",
        "author": "Isaac Asimov"
    }, {
        "title": "WATERSHIP DOWN",
        "author": "Richard Adams"
    }, {
        "title": "'SALEM'S LOT",
        "author": "Stephen King"
    }, {
        "title": "THE FOUNTAINS OF PARADISE",
        "author": "Arthur C. Clarke"
    }, {
        "title": "THE RISE OF ENDYMION",
        "author": "Dan Simmons"
    }, {
        "title": "THE SUBTLE KNIFE",
        "author": "Philip Pullman"
    }, {
        "title": "READY PLAYER ONE",
        "author": "Ernest Cline"
    }, {
        "title": "TO SAY NOTHING OF THE DOG",
        "author": "Connie Willis"
    }, {
        "title": "MOSTLY HARMLESS",
        "author": "Douglas Adams"
    }, {
        "title": "BABEL-17",
        "author": "Samuel R. Delany"
    }, {
        "title": "THE MARTIAN",
        "author": "Andy Weir"
    }, {
        "title": "THE THREE-BODY PROBLEM",
        "author": "Cixin Liu"
    }, {
        "title": "THE YIDDISH POLICEMEN'S UNION",
        "author": "Michael Chabon"
    }, {
        "title": "COUNT ZERO",
        "author": "William Gibson"
    }, {
        "title": "PRINCE CASPIAN",
        "author": "C. S. Lewis"
    }, {
        "title": "THE OCEAN AT THE END OF THE LANE",
        "author": "Neil Gaiman"
    }, {
        "title": "ENDYMION",
        "author": "Dan Simmons"
    }, {
        "title": "DOUBLE STAR",
        "author": "Robert A. Heinlein"
    }, {
        "title": "THE TOMBS OF ATUAN",
        "author": "Ursula K. Le Guin"
    }, {
        "title": "JOURNEY TO THE CENTER OF THE EARTH",
        "author": "Jules Verne"
    }, {
        "title": "THE LIGHT FANTASTIC",
        "author": "Terry Pratchett"
    }, {
        "title": "PRELUDE TO FOUNDATION",
        "author": "Isaac Asimov"
    }, {
        "title": "SOMETHING WICKED THIS WAY COMES",
        "author": "Ray Bradbury"
    }, {
        "title": "MONA LISA OVERDRIVE",
        "author": "William Gibson"
    }, {
        "title": "FOREVER PEACE",
        "author": "Joe Haldeman"
    }, {
        "title": "REVELATION SPACE",
        "author": "Alastair Reynolds"
    }, {
        "title": "GOD EMPEROR OF DUNE",
        "author": "Frank Herbert"
    }, {
        "title": "THE CLAW OF THE CONCILIATOR",
        "author": "Gene Wolfe"
    }, {
        "title": "GULLIVER'S TRAVELS",
        "author": "Jonathan Swift"
    }, {
        "title": "THE INVISIBLE MAN",
        "author": "H. G. Wells"
    }, {
        "title": "RAINBOWS END",
        "author": "Vernor Vinge"
    }, {
        "title": "THE PLAYER OF GAMES",
        "author": "Iain M. Banks"
    }, {
        "title": "THE ROBOTS OF DAWN",
        "author": "Isaac Asimov"
    }, {
        "title": "LORD FOUL'S BANE",
        "author": "Stephen R. Donaldson"
    }, {
        "title": "ALTERED CARBON",
        "author": "Richard K. Morgan"
    }, {
        "title": "THE VOYAGE OF THE DAWN TREADER",
        "author": "C. S. Lewis"
    }, {
        "title": "THE POSTMAN",
        "author": "David Brin"
    }, {
        "title": "THE LAST COLONY",
        "author": "John Scalzi"
    }, {
        "title": "STAND ON ZANZIBAR",
        "author": "John Brunner"
    }, {
        "title": "DARWIN'S RADIO",
        "author": "Greg Bear"
    }, {
        "title": "MISTBORN",
        "author": "Brandon Sanderson"
    }, {
        "title": "THE SANDMAN: PRELUDES AND NOCTURNES",
        "author": "Neil Gaiman"
    }, {
        "title": "BLUE MARS",
        "author": "Kim Stanley Robinson"
    }, {
        "title": "THE NAKED SUN",
        "author": "Isaac Asimov"
    }, {
        "title": "WAY STATION",
        "author": "Clifford D. Simak"
    }, {
        "title": "A WRINKLE IN TIME",
        "author": "Madeleine L’Engle"
    }, {
        "title": "MORT",
        "author": "Terry Pratchett"
    }, {
        "title": "THE UPLIFT WAR",
        "author": "David Brin"
    }, {
        "title": "THE FARTHEST SHORE",
        "author": "Ursula K. Le Guin"
    }, {
        "title": "EMBASSYTOWN",
        "author": "China Miéville"
    }, {
        "title": "THE ISLAND OF DR. MOREAU",
        "author": "H. G. Wells"
    }, {
        "title": "BARRAYAR",
        "author": "Lois McMaster Bujold"
    }, {
        "title": "LITTLE BROTHER",
        "author": "Cory Doctorow"
    }, {
        "title": "THROUGH THE LOOKING-GLASS, AND WHAT ALICE FOUND THERE",
        "author": "Lewis Carroll"
    }, {
        "title": "THE TIME MACHINE AND THE WAR OF THE WORLDS",
        "author": "H. G. Wells"
    }, {
        "title": "A PRINCESS OF MARS",
        "author": "Edgar Rice Burroughs"
    }, {
        "title": "THE ILLUSTRATED MAN",
        "author": "Ray Bradbury"
    }, {
        "title": "ANCILLARY SWORD",
        "author": "Ann Leckie"
    }, {
        "title": "HAVE SPACE SUIT - WILL TRAVEL",
        "author": "Robert A. Heinlein"
    }, {
        "title": "THE DRAWING OF THE THREE",
        "author": "Stephen King"
    }, {
        "title": "FLOW MY TEARS, THE POLICEMAN SAID",
        "author": "Philip K. Dick"
    }, {
        "title": "THE MAGICIAN'S NEPHEW",
        "author": "C. S. Lewis"
    }, {
        "title": "DRAGONQUEST",
        "author": "Anne McCaffrey"
    }, {
        "title": "WORLD WAR Z",
        "author": "Max Brooks"
    }, {
        "title": "CARRIE",
        "author": "Stephen King"
    }, {
        "title": "BONESHAKER",
        "author": "Cherie Priest"
    }, {
        "title": "SOLARIS",
        "author": "Stanislaw Lem"
    }, {
        "title": "EQUAL RITES",
        "author": "Terry Pratchett"
    }, {
        "title": "THE PRINCESS BRIDE",
        "author": "William Goldman"
    }, {
        "title": "BLACKOUT",
        "author": "Connie Willis"
    }, {
        "title": "THE SILVER CHAIR",
        "author": "C. S. Lewis"
    }, {
        "title": "THE HORSE AND HIS BOY",
        "author": "C. S. Lewis"
    }, {
        "title": "LUCIFER'S HAMMER",
        "author": "Larry NivenJerry Pournelle"
    }, {
        "title": "MORE THAN HUMAN",
        "author": "Theodore Sturgeon"
    }, {
        "title": "CONTACT",
        "author": "Carl Sagan"
    }, {
        "title": "USE OF WEAPONS",
        "author": "Iain M. Banks"
    }, {
        "title": "THE VOR GAME",
        "author": "Lois McMaster Bujold"
    }, {
        "title": "THE SCAR",
        "author": "China Miéville"
    }, {
        "title": "CHILDREN OF THE MIND",
        "author": "Orson Scott Card"
    }, {
        "title": "PET SEMATARY",
        "author": "Stephen King"
    }, {
        "title": "BLOOD MUSIC",
        "author": "Greg Bear"
    }, {
        "title": "ANNIHILATION",
        "author": "Jeff VanderMeer"
    }, {
        "title": "THE THREE STIGMATA OF PALMER ELDRITCH",
        "author": "Philip K. Dick"
    }, {
        "title": "SHARDS OF HONOR",
        "author": "Lois McMaster Bujold"
    }, {
        "title": "THE SPARROW",
        "author": "Mary Doria Russell"
    }, {
        "title": "THE SWORD OF THE LICTOR",
        "author": "Gene Wolfe"
    }, {
        "title": "THE BOOK OF THE NEW SUN, VOLUME 1",
        "author": "Gene Wolfe"
    }, {
        "title": "THE CITY AND THE STARS",
        "author": "Arthur C. Clarke"
    }, {
        "title": "SMALL GODS",
        "author": "Terry Pratchett"
    }, {
        "title": "TEHANU",
        "author": "Ursula K. Le Guin"
    }, {
        "title": "SEVENTH SON",
        "author": "Orson Scott Card"
    }, {
        "title": "THE MISTS OF AVALON",
        "author": "Marion Zimmer Bradley"
    }, {
        "title": "THE WASTE LANDS",
        "author": "Stephen King"
    }, {
        "title": "JURASSIC PARK",
        "author": "Michael Crichton"
    }, {
        "title": "TIME ENOUGH FOR LOVE",
        "author": "Robert A. Heinlein"
    }, {
        "title": "THE CHRONICLES OF AMBER",
        "author": "Roger Zelazny"
    }, {
        "title": "GOING POSTAL",
        "author": "Terry Pratchett"
    }, {
        "title": "THE GHOST BRIGADES",
        "author": "John Scalzi"
    }, {
        "title": "THE LITTLE PRINCE",
        "author": "Antoine de Saint-Exupery"
    }, {
        "title": "WHERE LATE THE SWEET BIRDS SANG",
        "author": "Kate Wilhelm"
    }, {
        "title": "NINE PRINCES IN AMBER",
        "author": "Roger Zelazny"
    }, {
        "title": "THE SWORD OF SHANNARA",
        "author": "Terry Brooks"
    }, {
        "title": "THE WHITE DRAGON",
        "author": "Anne McCaffrey"
    }, {
        "title": "THE RINGWORLD ENGINEERS",
        "author": "Larry Niven"
    }, {
        "title": "A CASE OF CONSCIENCE",
        "author": "James Blish"
    }, {
        "title": "MISERY",
        "author": "Stephen King"
    }, {
        "title": "THE GIVER",
        "author": "Lois Lowry"
    }, {
        "title": "PAWN OF PROPHECY",
        "author": "David Eddings"
    }, {
        "title": "DOWNBELOW STATION",
        "author": "C. J. Cherryh"
    }, {
        "title": "SHADOW OF THE HEGEMON",
        "author": "Orson Scott Card"
    }, {
        "title": "THE DIFFERENCE ENGINE",
        "author": "William GibsonBruce Sterling"
    }, {
        "title": "THE HUNDRED THOUSAND KINGDOMS",
        "author": "N. K. Jemisin"
    }, {
        "title": "THE TIME TRAVELER'S WIFE",
        "author": "Audrey Niffenegger"
    }, {
        "title": "SUNDIVER",
        "author": "David Brin"
    }, {
        "title": "THE WISE MAN'S FEAR",
        "author": "Patrick Rothfuss"
    }, {
        "title": "ACCELERANDO",
        "author": "Charles Stross"
    }, {
        "title": "PYRAMIDS",
        "author": "Terry Pratchett"
    }, {
        "title": "ILIUM",
        "author": "Dan Simmons"
    }, {
        "title": "DIRK GENTLY'S HOLISTIC DETECTIVE AGENCY",
        "author": "Douglas Adams"
    }, {
        "title": "GUARDS! GUARDS!",
        "author": "Terry Pratchett"
    }, {
        "title": "THE LAST BATTLE",
        "author": "C. S. Lewis"
    }, {
        "title": "ASSASSIN'S APPRENTICE",
        "author": "Robin Hobb"
    }, {
        "title": "STORM FRONT",
        "author": "Jim Butcher"
    }, {
        "title": "FRIDAY",
        "author": "Robert A. Heinlein"
    }, {
        "title": "A SPELL FOR CHAMELEON",
        "author": "Piers Anthony"
    }, {
        "title": "THE CITADEL OF THE AUTARCH",
        "author": "Gene Wolfe"
    }, {
        "title": "THE DEAD ZONE",
        "author": "Stephen King"
    }, {
        "title": "TIMESCAPE",
        "author": "Gregory Benford"
    }, {
        "title": "OUT OF THE SILENT PLANET",
        "author": "C. S. Lewis"
    }, {
        "title": "THE GREAT HUNT",
        "author": "Robert Jordan"
    }, {
        "title": "HERETICS OF DUNE",
        "author": "Frank Herbert"
    }, {
        "title": "CORALINE",
        "author": "Neil Gaiman"
    }, {
        "title": "THE VAMPIRE LESTAT",
        "author": "Anne Rice"
    }, {
        "title": "WYRD SISTERS",
        "author": "Terry Pratchett"
    }, {
        "title": "TAU ZERO",
        "author": "Poul Anderson"
    }, {
        "title": "THE CURSE OF CHALION",
        "author": "Lois McMaster Bujold"
    }, {
        "title": "ROBOTS AND EMPIRE",
        "author": "Isaac Asimov"
    }, {
        "title": "WIZARD AND GLASS",
        "author": "Stephen King"
    }, {
        "title": "FALLING FREE",
        "author": "Lois McMaster Bujold"
    }, {
        "title": "MIRROR DANCE",
        "author": "Lois McMaster Bujold"
    }, {
        "title": "WOLVES OF THE CALLA",
        "author": "Stephen King"
    }, {
        "title": "CLOUD ATLAS",
        "author": "David Mitchell"
    }, {
        "title": "THE ANDROMEDA STRAIN",
        "author": "Michael Crichton"
    }, {
        "title": "THE DRAGON REBORN",
        "author": "Robert Jordan"
    }, {
        "title": "THE LIES OF LOCKE LAMORA",
        "author": "Scott Lynch"
    }, {
        "title": "MAKING MONEY",
        "author": "Terry Pratchett"
    }, {
        "title": "THE SNOW QUEEN",
        "author": "Joan D. Vinge"
    }, {
        "title": "FORWARD THE FOUNDATION",
        "author": "Isaac Asimov"
    }, {
        "title": "THE GUNS OF AVALON",
        "author": "Roger Zelazny"
    }, {
        "title": "BLINDSIGHT",
        "author": "Peter Watts"
    }, {
        "title": "HOGFATHER",
        "author": "Terry Pratchett"
    }, {
        "title": "EXCESSION",
        "author": "Iain M. Banks"
    }, {
        "title": "THE WELL OF ASCENSION",
        "author": "Brandon Sanderson"
    }, {
        "title": "LORD OF CHAOS",
        "author": "Robert Jordan"
    }, {
        "title": "THIS IMMORTAL",
        "author": "Roger Zelazny"
    }, {
        "title": "VIRTUAL LIGHT",
        "author": "William Gibson"
    }, {
        "title": "THE END OF ETERNITY",
        "author": "Isaac Asimov"
    }, {
        "title": "CALIBAN'S WAR",
        "author": "James S. A. Corey"
    }, {
        "title": "NIGHT WATCH",
        "author": "Terry Pratchett"
    }, {
        "title": "CHAPTERHOUSE DUNE",
        "author": "Frank Herbert"
    }, {
        "title": "PRENTICE ALVIN",
        "author": "Orson Scott Card"
    }, {
        "title": "REAPER MAN",
        "author": "Terry Pratchett"
    }, {
        "title": "SONG OF SUSANNAH",
        "author": "Stephen King"
    }, {
        "title": "WIZARD'S FIRST RULE",
        "author": "Terry Goodkind"
    }, {
        "title": "PATTERN RECOGNITION",
        "author": "William Gibson"
    }, {
        "title": "THE HERO OF AGES",
        "author": "Brandon Sanderson"
    }, {
        "title": "THE SHADOW RISING",
        "author": "Robert Jordan"
    }, {
        "title": "THE ANUBIS GATES",
        "author": "Tim Powers"
    }, {
        "title": "THE PUPPET MASTERS",
        "author": "Robert A. Heinlein"
    }, {
        "title": "JOB",
        "author": "Robert A. Heinlein"
    }, {
        "title": "BEYOND THE BLUE EVENT HORIZON",
        "author": "Frederik Pohl"
    }, {
        "title": "RED PROPHET",
        "author": "Orson Scott Card"
    }, {
        "title": "A CONNECTICUT YANKEE IN KING ARTHUR'S COURT",
        "author": "Mark Twain"
    }, {
        "title": "STATION ELEVEN",
        "author": "Emily St. John Mandel"
    }, {
        "title": "HEIR TO THE EMPIRE",
        "author": "Timothy Zahn"
    }, {
        "title": "FIGHT CLUB",
        "author": "Chuck Palahniuk"
    }, {
        "title": "MAGICIAN: APPRENTICE",
        "author": "Raymond E. Feist"
    }, {
        "title": "MARTIAN TIME-SLIP",
        "author": "Philip K. Dick"
    }, {
        "title": "WE",
        "author": "Yevgeny Zamyatin"
    }, {
        "title": "MEMORY",
        "author": "Lois McMaster Bujold"
    }, {
        "title": "A CIVIL CAMPAIGN",
        "author": "Lois McMaster Bujold"
    }, {
        "title": "THE FIRES OF HEAVEN",
        "author": "Robert Jordan"
    }, {
        "title": "MEN AT ARMS",
        "author": "Terry Pratchett"
    }, {
        "title": "RAMA II",
        "author": "Gentry LeeArthur C. Clarke"
    }, {
        "title": "IRON COUNCIL",
        "author": "China Miéville"
    }, {
        "title": "CITY",
        "author": "Clifford D. Simak"
    }, {
        "title": "THE ALGEBRAIST",
        "author": "Iain M. Banks"
    }, {
        "title": "THE FIFTH SEASON",
        "author": "N. K. Jemisin"
    }, {
        "title": "SIGN OF THE UNICORN",
        "author": "Roger Zelazny"
    }, {
        "title": "THE WAY OF KINGS",
        "author": "Brandon Sanderson"
    }, {
        "title": "THE SILENCE OF THE LAMBS",
        "author": "Thomas Harris"
    }, {
        "title": "THE FIFTH ELEPHANT",
        "author": "Terry Pratchett"
    }, {
        "title": "ELRIC OF MELNIBONÉ",
        "author": "Michael Moorcock"
    }, {
        "title": "WITCHES ABROAD",
        "author": "Terry Pratchett"
    }, {
        "title": "ERIC",
        "author": "Terry Pratchett"
    }, {
        "title": "THE BIG TIME",
        "author": "Fritz Leiber"
    }, {
        "title": "CYTEEN",
        "author": "C. J. Cherryh"
    }, {
        "title": "THE METAMORPHOSIS",
        "author": "Franz Kafka"
    }, {
        "title": "THE INTEGRAL TREES",
        "author": "Larry Niven"
    }, {
        "title": "DYING INSIDE",
        "author": "Robert Silverberg"
    }, {
        "title": "WICKED",
        "author": "Gregory Maguire"
    }, {
        "title": "THE DROWNED WORLD",
        "author": "J. G. Ballard"
    }, {
        "title": "GRASS",
        "author": "Sheri S. Tepper"
    }, {
        "title": "FEET OF CLAY",
        "author": "Terry Pratchett"
    }, {
        "title": "MOVING PICTURES",
        "author": "Terry Pratchett"
    }, {
        "title": "ABADDON'S GATE",
        "author": "James S. A. Corey"
    }, {
        "title": "CETAGANDA",
        "author": "Lois McMaster Bujold"
    }, {
        "title": "2061",
        "author": "Arthur C. Clarke"
    }, {
        "title": "QUEEN OF SORCERY",
        "author": "David Eddings"
    }, {
        "title": "MISSION OF GRAVITY",
        "author": "Hal Clement"
    }, {
        "title": "THE WOUNDED LAND",
        "author": "Stephen R. Donaldson"
    }, {
        "title": "THE LONG DARK TEA-TIME OF THE SOUL",
        "author": "Douglas Adams"
    }, {
        "title": "THE HAND OF OBERON",
        "author": "Roger Zelazny"
    }, {
        "title": "THE SANDMAN: THE DOLL'S HOUSE",
        "author": "Neil Gaiman"
    }, {
        "title": "KRAKEN",
        "author": "China Miéville"
    }, {
        "title": "FOOL MOON",
        "author": "Jim Butcher"
    }, {
        "title": "THIEF OF TIME",
        "author": "Terry Pratchett"
    }, {
        "title": "THE EINSTEIN INTERSECTION",
        "author": "Samuel R. Delany"
    }, {
        "title": "THE COURTS OF CHAOS",
        "author": "Roger Zelazny"
    }, {
        "title": "ROYAL ASSASSIN",
        "author": "Robin Hobb"
    }, {
        "title": "THE WASP FACTORY",
        "author": "Iain M. Banks"
    }, {
        "title": "DR. BLOODMONEY",
        "author": "Philip K. Dick"
    }, {
        "title": "LORD VALENTINE'S CASTLE",
        "author": "Robert Silverberg"
    }, {
        "title": "CRYOBURN",
        "author": "Lois McMaster Bujold"
    }, {
        "title": "THE GOBLIN EMPEROR",
        "author": "Katherine Addison"
    }, {
        "title": "FIRESTARTER",
        "author": "Stephen King"
    }, {
        "title": "SOUL MUSIC",
        "author": "Terry Pratchett"
    }, {
        "title": "THUD!",
        "author": "Terry Pratchett"
    }, {
        "title": "CHASM CITY",
        "author": "Alastair Reynolds"
    }, {
        "title": "REDEMPTION ARK",
        "author": "Alastair Reynolds"
    }, {
        "title": "ORYX AND CRAKE",
        "author": "Margaret Atwood"
    }, {
        "title": "MONSTROUS REGIMENT",
        "author": "Terry Pratchett"
    }, {
        "title": "SINGULARITY SKY",
        "author": "Charles Stross"
    }, {
        "title": "MAGICIAN'S GAMBIT",
        "author": "David Eddings"
    }, {
        "title": "THE LAST UNICORN",
        "author": "Peter S. Beagle"
    }, {
        "title": "CITIES IN FLIGHT",
        "author": "James Blish"
    }, {
        "title": "VALIS",
        "author": "Philip K. Dick"
    }, {
        "title": "NEVER LET ME GO",
        "author": "Kazuo Ishiguro"
    }, {
        "title": "FOOTFALL",
        "author": "Larry NivenJerry Pournelle"
    }, {
        "title": "SPHERE",
        "author": "Michael Crichton"
    }, {
        "title": "THE HAUNTING OF HILL HOUSE",
        "author": "Shirley Jackson"
    }, {
        "title": "THE YEARS OF RICE AND SALT",
        "author": "Kim Stanley Robinson"
    }, {
        "title": "THE TALISMAN",
        "author": "Stephen KingPeter Straub"
    }, {
        "title": "NEEDFUL THINGS",
        "author": "Stephen King"
    }, {
        "title": "LORDS AND LADIES",
        "author": "Terry Pratchett"
    }, {
        "title": "THE ILLEARTH WAR",
        "author": "Stephen R. Donaldson"
    }, {
        "title": "THE GREEN MILE",
        "author": "Stephen King"
    }, {
        "title": "DANGEROUS VISIONS",
        "author": "Harlan Ellison"
    }, {
        "title": "A CROWN OF SWORDS",
        "author": "Robert Jordan"
    }, {
        "title": "NOVA",
        "author": "Samuel R. Delany"
    }, {
        "title": "TITAN",
        "author": "John Varley"
    }, {
        "title": "ALL CLEAR",
        "author": "Connie Willis"
    }, {
        "title": "CAMOUFLAGE",
        "author": "Joe Haldeman"
    }, {
        "title": "INTERESTING TIMES",
        "author": "Terry Pratchett"
    }, {
        "title": "THE SANDMAN: DREAM COUNTRY",
        "author": "Neil Gaiman"
    }, {
        "title": "CASTLE OF WIZARDRY",
        "author": "David Eddings"
    }, {
        "title": "BEGGARS IN SPAIN",
        "author": "Nancy Kress"
    }, {
        "title": "THE WORD FOR WORLD IS FOREST",
        "author": "Ursula K. Le Guin"
    }, {
        "title": "THE BOOK OF THE NEW SUN, VOLUME 2",
        "author": "Gene Wolfe"
    }, {
        "title": "BROTHERS IN ARMS",
        "author": "Lois McMaster Bujold"
    }, {
        "title": "A FALL OF MOONDUST",
        "author": "Arthur C. Clarke"
    }, {
        "title": "PARABLE OF THE SOWER",
        "author": "Octavia E. Butler"
    }, {
        "title": "ZOO CITY",
        "author": "Lauren Beukes"
    }, {
        "title": "PASSAGE",
        "author": "Connie Willis"
    }, {
        "title": "ENCHANTERS' END GAME",
        "author": "David Eddings"
    }, {
        "title": "ASSASSIN'S QUEST",
        "author": "Robin Hobb"
    }, {
        "title": "GLORY ROAD",
        "author": "Robert A. Heinlein"
    }, {
        "title": "V FOR VENDETTA",
        "author": "Alan MooreDavid Lloyd"
    }, {
        "title": "MATTER",
        "author": "Iain M. Banks"
    }, {
        "title": "HALTING STATE",
        "author": "Charles Stross"
    }, {
        "title": "THE POWER THAT PRESERVES",
        "author": "Stephen R. Donaldson"
    }, {
        "title": "THE TRIAL",
        "author": "Franz Kafka"
    }, {
        "title": "PEBBLE IN THE SKY",
        "author": "Isaac Asimov"
    }, {
        "title": "BRIGHTNESS REEF",
        "author": "David Brin"
    }, {
        "title": "NON-STOP",
        "author": "Brian W. Aldiss"
    }, {
        "title": "THE QUEEN OF THE DAMNED",
        "author": "Anne Rice"
    }, {
        "title": "DIPLOMATIC IMMUNITY",
        "author": "Lois McMaster Bujold"
    }, {
        "title": "THE MANY-COLORED LAND",
        "author": "Julian May"
    }, {
        "title": "JINGO",
        "author": "Terry Pratchett"
    }, {
        "title": "THE FORGE OF GOD",
        "author": "Greg Bear"
    }, {
        "title": "THE TIME SHIPS",
        "author": "Stephen Baxter"
    }, {
        "title": "BEHOLD THE MAN",
        "author": "Michael Moorcock"
    }, {
        "title": "UNDER THE DOME",
        "author": "Stephen King"
    }, {
        "title": "THE SPEED OF DARK",
        "author": "Elizabeth Moon"
    }, {
        "title": "THE FIFTH HEAD OF CERBERUS",
        "author": "Gene Wolfe"
    }, {
        "title": "MASKERADE",
        "author": "Terry Pratchett"
    }, {
        "title": "AT THE MOUNTAINS OF MADNESS AND OTHER TALES OF TERROR",
        "author": "H. P. Lovecraft"
    }, {
        "title": "HELLICONIA SPRING",
        "author": "Brian W. Aldiss"
    }, {
        "title": "THE SANDMAN: SEASON OF MISTS",
        "author": "Neil Gaiman"
    }, {
        "title": "11/22/63",
        "author": "Stephen King"
    }, {
        "title": "ETHAN OF ATHOS",
        "author": "Lois McMaster Bujold"
    }, {
        "title": "THE MIDWICH CUCKOOS",
        "author": "John Wyndham"
    }, {
        "title": "THE STAINLESS STEEL RAT",
        "author": "Harry Harrison"
    }, {
        "title": "THE CHRYSALIDS",
        "author": "John Wyndham"
    }, {
        "title": "THE PATH OF DAGGERS",
        "author": "Robert Jordan"
    }, {
        "title": "THE STARS, LIKE DUST",
        "author": "Isaac Asimov"
    }, {
        "title": "ABSOLUTION GAP",
        "author": "Alastair Reynolds"
    }, {
        "title": "GARDENS OF THE MOON",
        "author": "Steven Erikson"
    }, {
        "title": "MOVING MARS",
        "author": "Greg Bear"
    }, {
        "title": "PERELANDRA",
        "author": "C. S. Lewis"
    }, {
        "title": "MORETA",
        "author": "Anne McCaffrey"
    }, {
        "title": "SHADOW PUPPETS",
        "author": "Orson Scott Card"
    }, {
        "title": "NIGHT SHIFT",
        "author": "Stephen King"
    }, {
        "title": "GRAVE PERIL",
        "author": "Jim Butcher"
    }, {
        "title": "THE INVERTED WORLD",
        "author": "Christopher Priest"
    }, {
        "title": "THE EXORCIST",
        "author": "William Peter Blatty"
    }, {
        "title": "THE SANDMAN: A GAME OF YOU",
        "author": "Neil Gaiman"
    }, {
        "title": "OLYMPOS",
        "author": "Dan Simmons"
    }, {
        "title": "THE MASTER AND MARGARITA",
        "author": "Mikhail Bulgakov"
    }, {
        "title": "THE MIST",
        "author": "Stephen King"
    }, {
        "title": "THE TRUTH",
        "author": "Terry Pratchett"
    }, {
        "title": "SATURN'S CHILDREN",
        "author": "Charles Stross"
    }, {
        "title": "THE ATROCITY ARCHIVES",
        "author": "Charles Stross"
    }, {
        "title": "THE CHRONOLITHS",
        "author": "Robert Charles Wilson"
    }, {
        "title": "THE EYRE AFFAIR",
        "author": "Jasper Fforde"
    }, {
        "title": "THE LAST CONTINENT",
        "author": "Terry Pratchett"
    }, {
        "title": "SEEKER",
        "author": "Jack McDevitt"
    }, {
        "title": "DEATHWORLD 1",
        "author": "Harry Harrison"
    }, {
        "title": "THE GARDEN OF RAMA",
        "author": "Arthur C. ClarkeGentry Lee"
    }, {
        "title": "ALL THE WEYRS OF PERN",
        "author": "Anne McCaffrey"
    }, {
        "title": "LOOK TO WINDWARD",
        "author": "Iain M. Banks"
    }, {
        "title": "TIME OUT OF JOINT",
        "author": "Philip K. Dick"
    }, {
        "title": "CALCULATING GOD",
        "author": "Robert J. Sawyer"
    }, {
        "title": "DORSAI!",
        "author": "Gordon R. Dickson"
    }, {
        "title": "THE LOST WORLD",
        "author": "Arthur Conan Doyle"
    }, {
        "title": "THE DERVISH HOUSE",
        "author": "Ian McDonald"
    }, {
        "title": "KINDRED",
        "author": "Octavia E. Butler"
    }, {
        "title": "THE GOLEM AND THE JINNI",
        "author": "Helene Wecker"
    }, {
        "title": "THE LOST WORLD",
        "author": "Michael Crichton"
    }, {
        "title": "THE WEE FREE MEN",
        "author": "Terry Pratchett"
    }, {
        "title": "PLAYER PIANO",
        "author": "Kurt Vonnegut, Jr."
    }, {
        "title": "THE TURN OF THE SCREW",
        "author": "Henry James"
    }, {
        "title": "INVERSIONS",
        "author": "Iain M. Banks"
    }, {
        "title": "CARPE JUGULUM",
        "author": "Terry Pratchett"
    }, {
        "title": "A MEMORY OF LIGHT",
        "author": "Robert JordanBrandon Sanderson"
    }, {
        "title": "THE ONE TREE",
        "author": "Stephen R. Donaldson"
    }, {
        "title": "KILN PEOPLE",
        "author": "David Brin"
    }, {
        "title": "ELRIC",
        "author": "Michael Moorcock"
    }, {
        "title": "THE NIGHT CIRCUS",
        "author": "Erin Morgenstern"
    }, {
        "title": "UNSEEN ACADEMICALS",
        "author": "Terry Pratchett"
    }, {
        "title": "THE SWORD IN THE STONE",
        "author": "T. H. White"
    }, {
        "title": "LAST AND FIRST MEN",
        "author": "Olaf Stapledon"
    }, {
        "title": "3001",
        "author": "Arthur C. Clarke"
    }, {
        "title": "WEAVEWORLD",
        "author": "Clive Barker"
    }, {
        "title": "DHALGREN",
        "author": "Samuel R. Delany"
    }, {
        "title": "THE PRESTIGE",
        "author": "Christopher Priest"
    }, {
        "title": "TRUMPS OF DOOM",
        "author": "Roger Zelazny"
    }, {
        "title": "SKELETON CREW",
        "author": "Stephen King"
    }, {
        "title": "WINTER'S HEART",
        "author": "Robert Jordan"
    }, {
        "title": "THAT HIDEOUS STRENGTH",
        "author": "C. S. Lewis"
    }, {
        "title": "GLASSHOUSE",
        "author": "Charles Stross"
    }, {
        "title": "DRAGONSONG",
        "author": "Anne McCaffrey"
    }, {
        "title": "ON BASILISK STATION",
        "author": "David Weber"
    }, {
        "title": "THE SYSTEM OF THE WORLD",
        "author": "Neal Stephenson"
    }, {
        "title": "KOMARR",
        "author": "Lois McMaster Bujold"
    }, {
        "title": "THE CURRENTS OF SPACE",
        "author": "Isaac Asimov"
    }, {
        "title": "SURFACE DETAIL",
        "author": "Iain M. Banks"
    }, {
        "title": "TITUS GROAN",
        "author": "Mervyn Peake"
    }, {
        "title": "CAPTAIN VORPATRIL'S ALLIANCE",
        "author": "Lois McMaster Bujold"
    }, {
        "title": "SUMMER KNIGHT",
        "author": "Jim Butcher"
    }, {
        "title": "THE ALLOY OF LAW",
        "author": "Brandon Sanderson"
    }, {
        "title": "WHITE GOLD WIELDER",
        "author": "Stephen R. Donaldson"
    }, {
        "title": "KING OF THE MURGOS",
        "author": "David Eddings"
    }, {
        "title": "RITE OF PASSAGE",
        "author": "Alexei Panshin"
    }, {
        "title": "FOUCAULT'S PENDULUM",
        "author": "Umberto Eco"
    }, {
        "title": "THE SANDMAN: FABLES & REFLECTIONS",
        "author": "Neil Gaiman"
    }, {
        "title": "THE AMAZING ADVENTURES OF KAVALIER & CLAY",
        "author": "Michael Chabon"
    }, {
        "title": "CROSSROADS OF TWILIGHT",
        "author": "Robert Jordan"
    }, {
        "title": "DEADLINE",
        "author": "Mira Grant"
    }, {
        "title": "SONG OF KALI",
        "author": "Dan Simmons"
    }, {
        "title": "LITTLE, BIG",
        "author": "John Crowley"
    }, {
        "title": "SHADOW OF THE GIANT",
        "author": "Orson Scott Card"
    }, {
        "title": "WWW: WAKE",
        "author": "Robert J. Sawyer"
    }, {
        "title": "SLAN",
        "author": "A. E. Van Vogt"
    }, {
        "title": "THE BOOK OF SKULLS",
        "author": "Robert Silverberg"
    }, {
        "title": "THE GATHERING STORM",
        "author": "Robert JordanBrandon Sanderson"
    }, {
        "title": "THE OTHER WIND",
        "author": "Ursula K. Le Guin"
    }, {
        "title": "FARMER IN THE SKY",
        "author": "Robert A. Heinlein"
    }, {
        "title": "ERAGON",
        "author": "Christopher Paolini"
    }, {
        "title": "ALVIN JOURNEYMAN",
        "author": "Orson Scott Card"
    }, {
        "title": "ALL THE BIRDS IN THE SKY",
        "author": "Charlie Jane Anders"
    }, {
        "title": "THE QUANTUM THIEF",
        "author": "Hannu Rajaniemi"
    }, {
        "title": "BLOOD OF AMBER",
        "author": "Roger Zelazny"
    }, {
        "title": "THE PICTURE OF DORIAN GRAY",
        "author": "Oscar Wilde"
    }, {
        "title": "BAG OF BONES",
        "author": "Stephen King"
    }, {
        "title": "PROTECTOR",
        "author": "Larry Niven"
    }, {
        "title": "THE PEACE WAR",
        "author": "Vernor Vinge"
    }, {
        "title": "THE WANDERER",
        "author": "Fritz Leiber"
    }, {
        "title": "THE SANDMAN: BRIEF LIVES",
        "author": "Neil Gaiman"
    }, {
        "title": "EARTH",
        "author": "David Brin"
    }, {
        "title": "PARABLE OF THE TALENTS",
        "author": "Octavia E. Butler"
    }, {
        "title": "KUSHIEL'S DART",
        "author": "Jacqueline Carey"
    }, {
        "title": "THE MAGICIANS",
        "author": "Lev Grossman"
    }, {
        "title": "THE SOURCE OF MAGIC",
        "author": "Piers Anthony"
    }, {
        "title": "AUTHORITY",
        "author": "Jeff VanderMeer"
    }, {
        "title": "REPLAY",
        "author": "Ken Grimwood"
    }, {
        "title": "THE LONG WAY TO A SMALL, ANGRY PLANET",
        "author": "Becky Chambers"
    }, {
        "title": "GALAPAGOS",
        "author": "Kurt Vonnegut, Jr."
    }, {
        "title": "THE BLADE ITSELF",
        "author": "Joe Abercrombie"
    }, {
        "title": "DOWN AND OUT IN THE MAGIC KINGDOM",
        "author": "Cory Doctorow"
    }, {
        "title": "LOCK IN",
        "author": "John Scalzi"
    }, {
        "title": "TOWERS OF MIDNIGHT",
        "author": "Robert JordanBrandon Sanderson"
    }, {
        "title": "BURNING CHROME (COLLECTION)",
        "author": "William Gibson"
    }, {
        "title": "STAR MAKER",
        "author": "Olaf Stapledon"
    }, {
        "title": "THE SAILOR ON THE SEAS OF FATE",
        "author": "Michael Moorcock"
    }, {
        "title": "THE CRYSTAL CAVE",
        "author": "Mary Stewart"
    }, {
        "title": "THE TERMINAL EXPERIMENT",
        "author": "Robert J. Sawyer"
    }, {
        "title": "FEERSUM ENDJINN",
        "author": "Iain M. Banks"
    }, {
        "title": "TIGANA",
        "author": "Guy Gavriel Kay"
    }, {
        "title": "DARK FORCE RISING",
        "author": "Timothy Zahn"
    }, {
        "title": "PUSHING ICE",
        "author": "Alastair Reynolds"
    }, {
        "title": "THE SANDMAN: WORLDS' END",
        "author": "Neil Gaiman"
    }, {
        "title": "ROCANNON'S WORLD",
        "author": "Ursula K. Le Guin"
    }, {
        "title": "KNIFE OF DREAMS",
        "author": "Robert Jordan"
    }, {
        "title": "ROSEMARY'S BABY",
        "author": "Ira Levin"
    }, {
        "title": "THE ENGINES OF GOD",
        "author": "Jack McDevitt"
    }, {
        "title": "RAMA REVEALED",
        "author": "Arthur C. ClarkeGentry Lee"
    }, {
        "title": "A HAT FULL OF SKY",
        "author": "Terry Pratchett"
    }, {
        "title": "THE SANDMAN: THE KINDLY ONES",
        "author": "Neil Gaiman"
    }, {
        "title": "TIMELINE",
        "author": "Michael Crichton"
    }, {
        "title": "THE EYES OF THE DRAGON",
        "author": "Stephen King"
    }, {
        "title": "THE FEMALE MAN",
        "author": "Joanna Russ"
    }, {
        "title": "HEECHEE RENDEZVOUS",
        "author": "Frederik Pohl"
    }, {
        "title": "ALAS, BABYLON",
        "author": "Pat Frank"
    }, {
        "title": "THE ACCIDENTAL TIME MACHINE",
        "author": "Joe Haldeman"
    }, {
        "title": "INSOMNIA",
        "author": "Stephen King"
    }, {
        "title": "THE GIRL WITH ALL THE GIFTS",
        "author": "M. R. Carey"
    }, {
        "title": "HOTHOUSE / THE LONG AFTERNOON OF EARTH",
        "author": "Brian W. Aldiss"
    }, {
        "title": "DEATH MASKS",
        "author": "Jim Butcher"
    }, {
        "title": "FLATLAND",
        "author": "Edwin A. Abbott"
    }, {
        "title": "IRON SUNRISE",
        "author": "Charles Stross"
    }, {
        "title": "WORDS OF RADIANCE",
        "author": "Brandon Sanderson"
    }, {
        "title": "THRONE OF THE CRESCENT MOON",
        "author": "Saladin Ahmed"
    }, {
        "title": "DANDELION WINE",
        "author": "Ray Bradbury"
    }, {
        "title": "THE SANDMAN: THE WAKE",
        "author": "Neil Gaiman"
    }, {
        "title": "THE LOVELY BONES",
        "author": "Alice Sebold"
    }, {
        "title": "HOUSE OF SUNS",
        "author": "Alastair Reynolds"
    }, {
        "title": "THE CONFUSION",
        "author": "Neal Stephenson"
    }, {
        "title": "MAKE ROOM! MAKE ROOM!",
        "author": "Harry Harrison"
    }, {
        "title": "BELOVED",
        "author": "Toni Morrison"
    }, {
        "title": "IDORU",
        "author": "William Gibson"
    }, {
        "title": "OUTLANDER",
        "author": "Diana Gabaldon"
    }, {
        "title": "LITTLE FUZZY",
        "author": "H. Beam Piper"
    }, {
        "title": "THE LAST COMMAND",
        "author": "Timothy Zahn"
    }, {
        "title": "THE STATE OF THE ART",
        "author": "Iain M. Banks"
    }, {
        "title": "DUNE",
        "author": "Frank Herbert"
    }, {
        "title": "SIGN OF CHAOS",
        "author": "Roger Zelazny"
    }]
}